genn/Document.py
genn/__init__.py
genn/controllers.py
genn/embedding.py
genn/generator.py
genn/gpt2.py
genn/gpt2_summarizer.py
genn/gru.py
genn/importers.py
genn/lstm.py
genn/preprocessing.py
genn-0.7.7.dist-info/LICENSE.txt
genn-0.7.7.dist-info/METADATA
genn-0.7.7.dist-info/WHEEL
genn-0.7.7.dist-info/top_level.txt
genn-0.7.7.dist-info/RECORD
