Metadata-Version: 2.1
Name: genn
Version: 0.7.7
Summary: GeNN (Generative Neural Networks) is a high-level interface for text applications using PyTorch
Home-page: https://github.com/FahedSabellioglu/genn
Author: Fahed Sabellioglu, Abdelrahman Mahmoud
Author-email: abdohossan@gmail.com, sabellioglu@gmail.com
License: MIT
Platform: UNKNOWN
Requires-Python: >=3.0
License-File: LICENSE.txt
Requires-Dist: torch
Requires-Dist: torchtext
Requires-Dist: pytorch-transformers
Requires-Dist: fasttext
